macos_notifier.py
tests/__init__.py
tests/test_cron.py
macos_notifier-1.0.3.dist-info/LICENSE
macos_notifier-1.0.3.dist-info/METADATA
macos_notifier-1.0.3.dist-info/WHEEL
macos_notifier-1.0.3.dist-info/entry_points.txt
macos_notifier-1.0.3.dist-info/top_level.txt
macos_notifier-1.0.3.dist-info/RECORD
