Metadata-Version: 2.1
Name: macos-notifier
Version: 1.0.3
Summary: MacOS custom notifications manager
Home-page: https://github.com/dasdachs/macos-notifier
Author: Jani Šumak
Author-email: jani.sumak@gmail.com
License: UNKNOWN
Platform: UNKNOWN
Classifier: Environment :: Console
Classifier: Programming Language :: Python :: 3
Classifier: License :: OSI Approved :: MIT License
Classifier: Environment :: MacOS X
Requires-Python: >=3.7
Requires-Dist: Click
Requires-Dist: Colorama
Requires-Dist: python-crontab
